LICENSE.txt
MANIFEST.in
README.rst
requirements.txt
setup.cfg
setup.py
iwant/__init__.py
iwant.egg-info/PKG-INFO
iwant.egg-info/SOURCES.txt
iwant.egg-info/dependency_links.txt
iwant.egg-info/entry_points.txt
iwant.egg-info/pbr.json
iwant.egg-info/requires.txt
iwant.egg-info/top_level.txt
iwant/cli/__init__.py
iwant/cli/main.py
iwant/cli/utils.py
iwant/core/__init__.py
iwant/core/config.py
iwant/core/constants.py
iwant/core/exception.py
iwant/core/messagebaker.py
iwant/core/protocols.py
iwant/core/engine/__init__.py
iwant/core/engine/client.py
iwant/core/engine/identity.py
iwant/core/engine/server.py
iwant/core/engine/consensus/__init__.py
iwant/core/engine/consensus/beacon.py
iwant/core/engine/fileindexer/__init__.py
iwant/core/engine/fileindexer/fileHashUtils.py
iwant/core/engine/fileindexer/piece.py
iwant/core/engine/monitor/__init__.py
iwant/core/engine/monitor/callbacks.py
iwant/core/engine/monitor/watching.py