Metadata-Version: 1.1
Name: iwant
Version: 1.0.14
Summary: CLI based decentralized peer to peer file sharing
Home-page: https://github.com/nirvik/iWant
Author: Nirvik Ghosh
Author-email: nirvik1993@gmail.com
License: UNKNOWN
Platform: UNKNOWN
Classifier: Framework :: Twisted
Classifier: Topic :: Communications :: File Sharing
Classifier: Topic :: System :: Networking
Classifier: Topic :: System :: Operating System
Classifier: Intended Audience :: Developers
Classifier: License :: OSI Approved :: MIT License
